{
  "id": "101A",
  "contest_id": 101,
  "index": "A",
  "name": "Homework",
  "difficulty": 1200,
  "tags": [
    "greedy"
  ],
  "url": "https://codeforces.com/problemset/problem/101/A",
  "time_limit": "2 seconds",
  "memory_limit": "256 megabytes",
  "statement": "Once when Gerald studied in the first year at school, his teacher gave the class the following homework. She offered the students a string consisting of n small Latin letters; the task was to learn the way the letters that the string contains are written. However, as Gerald is too lazy, he has no desire whatsoever to learn those letters. That's why he decided to lose some part of the string (not necessarily a connected part). The lost part can consist of any number of segments of any length, at any distance from each other. However, Gerald knows that if he loses more than k characters, it will be very suspicious.\nFind the least number of distinct characters that can remain in the string after no more than k characters are deleted. You also have to find any possible way to delete the characters.",
  "input": "Input",
  "output": "",
  "samples": [],
  "note": "",
  "hints": [],
  "tutorial": ""
}