{
  "id": "1116A2",
  "contest_id": 1116,
  "index": "A2",
  "name": "Generate equal superposition of four basis states",
  "difficulty": 0,
  "tags": [
    "*special"
  ],
  "url": "https://codeforces.com/problemset/problem/1116/A2",
  "time_limit": "1 second",
  "memory_limit": "256 megabytes",
  "statement": "You are given $N$ qubits in the zero state $|0...0 \\rangle$. You are also given four distinct bit vectors which describe four different basis states on $N$ qubits $|\\psi_i \\rangle$.\nYour task is to generate a state which is an equal superposition of the given basis states:\n$$|S \\rangle = \\frac{1}{2} \\big( |\\psi_0 \\rangle + |\\psi_1 \\rangle + |\\psi_2 \\rangle + |\\psi_3 \\rangle \\big)$$\nYou have to implement an operation which takes the following inputs:\n•  an array of $N$ ($2 \\le N \\le 16$) qubits,\n•  a two-dimensional array of Boolean values $bits$ representing the basis states $|\\psi_i \\rangle$. $bits$ will have exactly 4 elements, each of $bits[i]$ describing the basis state $|\\psi_i \\rangle$. Each of $bits[i]$ will have $N$ elements, $bits[i][j]$ giving the state of qubit $j$ in the basis state $|\\psi_i \\rangle$. Bit values true and false corresponding to $|1 \\rangle$ and $|0 \\rangle$ states, respectively; for example, for $N = 2$ an array [false, true] will represent the basis state $|01\\rangle$. Each pair of $bits[i]$ and $bits[j]$ will differ in at least one position for $i \\neq j$.\nThe operation doesn't have an output; its \"output\" is the state in which it leaves the qubits.\nYour code should have the following signature:\nnamespace Solution {\nopen Microsoft.Quantum.Primitive;\nopen Microsoft.Quantum.Canon;\noperation Solve (qs : Qubit[], bits : Bool[][]) : Unit {\n// your code here\n}\n}",
  "input": "",
  "output": "",
  "samples": [],
  "note": "",
  "hints": [],
  "tutorial": ""
}