{
  "id": "1228A",
  "contest_id": 1228,
  "index": "A",
  "name": "Distinct Digits",
  "difficulty": 800,
  "tags": [
    "brute force",
    "implementation"
  ],
  "url": "https://codeforces.com/problemset/problem/1228/A",
  "time_limit": "1 second",
  "memory_limit": "256 megabytes",
  "statement": "You have two integers $l$ and $r$. Find an integer $x$ which satisfies the conditions below:\n•  $l \\le x \\le r$.\n•  All digits of $x$ are different.\nIf there are multiple answers, print any of them.",
  "input": "The first line contains two integers $l$ and $r$ ($1 \\le l \\le r \\le 10^{5}$).",
  "output": "If an answer exists, print any of them. Otherwise, print $-1$.",
  "samples": [
    {
      "input": "121 130",
      "output": "123"
    },
    {
      "input": "98766 100000",
      "output": "-1"
    }
  ],
  "note": "In the first example, $123$ is one of the possible answers. However, $121$ can't be the answer, because there are multiple $1$s on different digits.\nIn the second example, there is no valid answer.",
  "hints": [],
  "tutorial": ""
}