{
  "id": "171C",
  "contest_id": 171,
  "index": "C",
  "name": "A Piece of Cake",
  "difficulty": 2000,
  "tags": [
    "*special",
    "implementation"
  ],
  "url": "https://codeforces.com/problemset/problem/171/C",
  "time_limit": "2 seconds",
  "memory_limit": "256 megabytes",
  "statement": "How to make a cake you'll never eat.\nIngredients.\n•  2 carrots\n•  0 calories\n•  100 g chocolate spread\n•  1 pack of flour\n•  1 egg\nMethod.\n•  Put calories into the mixing bowl.\n•  Take carrots from refrigerator.\n•  Chop carrots.\n•  Take chocolate spread from refrigerator.\n•  Put chocolate spread into the mixing bowl.\n•  Combine pack of flour into the mixing bowl.\n•  Fold chocolate spread into the mixing bowl.\n•  Add chocolate spread into the mixing bowl.\n•  Put pack of flour into the mixing bowl.\n•  Add egg into the mixing bowl.\n•  Fold pack of flour into the mixing bowl.\n•  Chop carrots until choped.\n•  Pour contents of the mixing bowl into the baking dish.\nServes 1.",
  "input": "Input",
  "output": "",
  "samples": [],
  "note": "",
  "hints": [],
  "tutorial": ""
}