{
  "id": "1765J",
  "contest_id": 1765,
  "index": "J",
  "name": "Hero to Zero",
  "difficulty": 2900,
  "tags": [
    "graph matchings",
    "math"
  ],
  "url": "https://codeforces.com/problemset/problem/1765/J",
  "time_limit": "4 seconds",
  "memory_limit": "512 megabytes",
  "statement": "There are no heroes in this problem. I guess we should have named it \"To Zero\".\nYou are given two arrays $a$ and $b$, each of these arrays contains $n$ non-negative integers.\nLet $c$ be a matrix of size $n \\times n$ such that $c_{i,j} = |a_i - b_j|$ for every $i \\in [1, n]$ and every $j \\in [1, n]$.\nYour goal is to transform the matrix $c$ so that it becomes the zero matrix, i. e. a matrix where every element is exactly $0$. In order to do so, you may perform the following operations any number of times, in any order:\n•  choose an integer $i$, then decrease $c_{i,j}$ by $1$ for every $j \\in [1, n]$ (i. e. decrease all elements in the $i$-th row by $1$). In order to perform this operation, you pay $1$ coin;\n•  choose an integer $j$, then decrease $c_{i,j}$ by $1$ for every $i \\in [1, n]$ (i. e. decrease all elements in the $j$-th column by $1$). In order to perform this operation, you pay $1$ coin;\n•  choose two integers $i$ and $j$, then decrease $c_{i,j}$ by $1$. In order to perform this operation, you pay $1$ coin;\n•  choose an integer $i$, then increase $c_{i,j}$ by $1$ for every $j \\in [1, n]$ (i. e. increase all elements in the $i$-th row by $1$). When you perform this operation, you receive $1$ coin;\n•  choose an integer $j$, then increase $c_{i,j}$ by $1$ for every $i \\in [1, n]$ (i. e. increase all elements in the $j$-th column by $1$). When you perform this operation, you receive $1$ coin.\nYou have to calculate the minimum number of coins required to transform the matrix $c$ into the zero matrix. Note that all elements of $c$ should be equal to $0$ simultaneously after the operations.",
  "input": "The first line contains one integer $n$ ($2 \\le n \\le 2 \\cdot 10^5$).\nThe second line contains $n$ integers $a_1, a_2, \\dots, a_n$ ($0 \\le a_i \\le 10^8$).\nThe third line contains $n$ integers $b_1, b_2, \\dots, b_n$ ($0 \\le b_j \\le 10^8$).",
  "output": "Print one integer — the minimum number of coins required to transform the matrix $c$ into the zero matrix.",
  "samples": [
    {
      "input": "3\n1 2 3\n2 2 2",
      "output": "2"
    },
    {
      "input": "3\n3 1 3\n1 1 2",
      "output": "5"
    },
    {
      "input": "2\n1 0\n2 1",
      "output": "2"
    },
    {
      "input": "2\n1 4\n2 3",
      "output": "4"
    },
    {
      "input": "4\n1 3 3 7\n6 9 4 2",
      "output": "29"
    }
  ],
  "note": "In the first example, the matrix looks as follows:\n111000111\nYou can turn it into a zero matrix using $2$ coins as follows:\n•  subtract $1$ from the first row, paying $1$ coin;\n•  subtract $1$ from the third row, paying $1$ coin.\nIn the second example, the matrix looks as follows:\n221001221\nYou can turn it into a zero matrix using $5$ coins as follows:\n•  subtract $1$ from the first row, paying $1$ coin;\n•  subtract $1$ from the third row, paying $1$ coin;\n•  subtract $1$ from the third row, paying $1$ coin;\n•  subtract $1$ from $a_{2,3}$, paying $1$ coin;\n•  add $1$ to the third column, receiving $1$ coin;\n•  subtract $1$ from the first row, paying $1$ coin;\n•  subtract $1$ from $a_{2,3}$, paying $1$ coin.",
  "hints": [],
  "tutorial": ""
}