{
  "id": "225C",
  "contest_id": 225,
  "index": "C",
  "name": "Barcode",
  "difficulty": 1700,
  "tags": [
    "dp",
    "matrices"
  ],
  "url": "https://codeforces.com/problemset/problem/225/C",
  "time_limit": "2 seconds",
  "memory_limit": "256 megabytes",
  "statement": "You've got an n × m pixel picture. Each pixel can be white or black. Your task is to change the colors of as few pixels as possible to obtain a barcode picture.\nA picture is a barcode if the following conditions are fulfilled:\n•  All pixels in each column are of the same color.\n•  The width of each monochrome vertical line is at least x and at most y pixels. In other words, if we group all neighbouring columns of the pixels with equal color, the size of each group can not be less than x or greater than y.",
  "input": "Input",
  "output": "",
  "samples": [],
  "note": "",
  "hints": [],
  "tutorial": ""
}