{
  "id": "234G",
  "contest_id": 234,
  "index": "G",
  "name": "Practice",
  "difficulty": 1600,
  "tags": [
    "constructive algorithms",
    "divide and conquer",
    "implementation"
  ],
  "url": "https://codeforces.com/problemset/problem/234/G",
  "time_limit": "1 second",
  "memory_limit": "256 megabytes",
  "statement": "Little time is left before Berland annual football championship. Therefore the coach of team \"Losewille Rangers\" decided to resume the practice, that were indefinitely interrupted for uncertain reasons. Overall there are n players in \"Losewille Rangers\". Each player on the team has a number — a unique integer from 1 to n. To prepare for the championship, the coach Mr. Floppe decided to spend some number of practices.\nMr. Floppe spent some long nights of his holiday planning how to conduct the practices. He came to a very complex practice system. Each practice consists of one game, all n players of the team take part in the game. The players are sorted into two teams in some way. In this case, the teams may have different numbers of players, but each team must have at least one player.\nThe coach wants to be sure that after the series of the practice sessions each pair of players had at least one practice, when they played in different teams. As the players' energy is limited, the coach wants to achieve the goal in the least number of practices.\nHelp him to schedule the practices.",
  "input": "Input",
  "output": "",
  "samples": [],
  "note": "",
  "hints": [],
  "tutorial": ""
}