{
  "id": "263E",
  "contest_id": 263,
  "index": "E",
  "name": "Rhombus",
  "difficulty": 2500,
  "tags": [
    "brute force",
    "data structures",
    "dp"
  ],
  "url": "https://codeforces.com/problemset/problem/263/E",
  "time_limit": "3 seconds",
  "memory_limit": "256 megabytes",
  "statement": "You've got a table of size n × m. On the intersection of the i-th row (1 ≤ i ≤ n) and the j-th column (1 ≤ j ≤ m) there is a non-negative integer ai, j. Besides, you've got a non-negative integer k.\nYour task is to find such pair of integers (a, b) that meets these conditions:\n•  k ≤ a ≤ n - k + 1;\n•  k ≤ b ≤ m - k + 1;\n•  let's denote the maximum of the function  among all integers x and y, that satisfy the inequalities k ≤ x ≤ n - k + 1 and k ≤ y ≤ m - k + 1, as mval; for the required pair of numbers the following equation must hold f(a, b) = mval.",
  "input": "Input",
  "output": "",
  "samples": [],
  "note": "",
  "hints": [],
  "tutorial": ""
}