{
  "id": "280D",
  "contest_id": 280,
  "index": "D",
  "name": "k-Maximum Subsequence Sum",
  "difficulty": 2800,
  "tags": [
    "data structures",
    "flows",
    "graphs",
    "implementation"
  ],
  "url": "https://codeforces.com/problemset/problem/280/D",
  "time_limit": "4 seconds",
  "memory_limit": "256 megabytes",
  "statement": "Consider integer sequence a1, a2, ..., an. You should run queries of two types:\n•  The query format is \"0 i val\". In reply to this query you should make the following assignment: ai = val.\n•  The query format is \"1 l r k\". In reply to this query you should print the maximum sum of at most k non-intersecting subsegments of sequence al, al + 1, ..., ar. Formally, you should choose at most k pairs of integers (x1, y1), (x2, y2), ..., (xt, yt) (l ≤ x1 ≤ y1 \u003c x2 ≤ y2 \u003c ... \u003c xt ≤ yt ≤ r; t ≤ k) such that the sum ax1 + ax1 + 1 + ... + ay1 + ax2 + ax2 + 1 + ... + ay2 + ... + axt + axt + 1 + ... + ayt is as large as possible. Note that you should choose at most k subsegments. Particularly, you can choose 0 subsegments. In this case the described sum considered equal to zero.",
  "input": "Input",
  "output": "",
  "samples": [],
  "note": "",
  "hints": [],
  "tutorial": ""
}