{
  "id": "286E",
  "contest_id": 286,
  "index": "E",
  "name": "Ladies' Shop",
  "difficulty": 2800,
  "tags": [
    "constructive algorithms",
    "fft",
    "math"
  ],
  "url": "https://codeforces.com/problemset/problem/286/E",
  "time_limit": "8 seconds",
  "memory_limit": "256 megabytes",
  "statement": "A ladies' shop has recently opened in the city of Ultima Thule. To get ready for the opening, the shop bought n bags. Each bag is characterised by the total weight ai of the items you can put there. The weird thing is, you cannot use these bags to put a set of items with the total weight strictly less than ai. However the weights of the items that will be sold in the shop haven't yet been defined. That's what you should determine right now.\nYour task is to find the set of the items' weights p1, p2, ..., pk (1 ≤ p1 \u003c p2 \u003c ... \u003c pk), such that:\n•  Any bag will be used. That is, for any i (1 ≤ i ≤ n) there will be such set of items that their total weight will equal ai. We assume that there is the infinite number of items of any weight. You can put multiple items of the same weight in one bag.\n•  For any set of items that have total weight less than or equal to m, there is a bag into which you can put this set. Similarly, a set of items can contain multiple items of the same weight.\n•  Of all sets of the items' weights that satisfy points 1 and 2, find the set with the minimum number of weights. In other words, value k should be as small as possible.\nFind and print the required set.",
  "input": "Input",
  "output": "",
  "samples": [],
  "note": "",
  "hints": [],
  "tutorial": ""
}