{
  "id": "28B",
  "contest_id": 28,
  "index": "B",
  "name": "pSort",
  "difficulty": 1600,
  "tags": [
    "dfs and similar",
    "dsu",
    "graphs"
  ],
  "url": "https://codeforces.com/problemset/problem/28/B",
  "time_limit": "2 seconds",
  "memory_limit": "256 megabytes",
  "statement": "One day n cells of some array decided to play the following game. Initially each cell contains a number which is equal to it's ordinal number (starting from 1). Also each cell determined it's favourite number. On it's move i-th cell can exchange it's value with the value of some other j-th cell, if |i - j| = di, where di is a favourite number of i-th cell. Cells make moves in any order, the number of moves is unlimited.\nThe favourite number of each cell will be given to you. You will also be given a permutation of numbers from 1 to n. You are to determine whether the game could move to this state.",
  "input": "Input",
  "output": "",
  "samples": [],
  "note": "",
  "hints": [],
  "tutorial": ""
}