{
  "contest_id": 362,
  "difficulty": 1100,
  "hints": [],
  "id": "362B",
  "index": "B",
  "input": "Input",
  "memory_limit": "256 megabytes",
  "name": "Petya and Staircases",
  "note": "",
  "output": "",
  "samples": [],
  "statement": "Little boy Petya loves stairs very much. But he is bored from simple going up and down them — he loves jumping over several stairs at a time. As he stands on some stair, he can either jump to the next one or jump over one or two stairs at a time. But some stairs are too dirty and Petya doesn't want to step on them.\nNow Petya is on the first stair of the staircase, consisting of n stairs. He also knows the numbers of the dirty stairs of this staircase. Help Petya find out if he can jump through the entire staircase and reach the last stair number n without touching a dirty stair once.\nOne has to note that anyway Petya should step on the first and last stairs, so if the first or the last stair is dirty, then Petya cannot choose a path with clean steps only.",
  "tags": [
    "implementation",
    "sortings"
  ],
  "time_limit": "1 second",
  "tutorial": "One has to note that the number of dirty stairs  ≤ 3000. Petya can reach stair number n if the first and the last stairs are not dirty and there are not three or more dirty stairs in a row. So let sort the array of dirty stairs and go through it, checking for three or more consecutive dirty stairs. Also one need to check if the first or the last stair is in this array.",
  "tutorial_url": "https://codeforces.com/blog/entry/9584",
  "url": "https://codeforces.com/problemset/problem/362/B"
}