{
  "id": "405C",
  "contest_id": 405,
  "index": "C",
  "name": "Unusual Product",
  "difficulty": 1600,
  "tags": [
    "implementation",
    "math"
  ],
  "url": "https://codeforces.com/problemset/problem/405/C",
  "time_limit": "1 second",
  "memory_limit": "256 megabytes",
  "statement": "Little Chris is a huge fan of linear algebra. This time he has been given a homework about the unusual square of a square matrix.\nThe dot product of two integer number vectors x and y of size n is the sum of the products of the corresponding components of the vectors. The unusual square of an n × n square matrix A is defined as the sum of n dot products. The i-th of them is the dot product of the i-th row vector and the i-th column vector in the matrix A.\nFortunately for Chris, he has to work only in GF(2)! This means that all operations (addition, multiplication) are calculated modulo 2. In fact, the matrix A is binary: each element of A is either 0 or 1. For example, consider the following matrix A:\nThe unusual square of A is equal to (1·1 + 1·0 + 1·1) + (0·1 + 1·1 + 1·0) + (1·1 + 0·1 + 0·0) = 0 + 1 + 1 = 0.\nHowever, there is much more to the homework. Chris has to process q queries; each query can be one of the following:\n•  given a row index i, flip all the values in the i-th row in A;\n•  given a column index i, flip all the values in the i-th column in A;\n•  find the unusual square of A.\nTo flip a bit value w means to change it to 1 - w, i.e., 1 changes to 0 and 0 changes to 1.\nGiven the initial matrix A, output the answers for each query of the third type! Can you solve Chris's homework?",
  "input": "Input",
  "output": "",
  "samples": [],
  "note": "",
  "hints": [],
  "tutorial": ""
}