{
  "id": "414B",
  "contest_id": 414,
  "index": "B",
  "name": "Mashmokh and ACM",
  "difficulty": 1400,
  "tags": [
    "combinatorics",
    "dp",
    "number theory"
  ],
  "url": "https://codeforces.com/problemset/problem/414/B",
  "time_limit": "1 second",
  "memory_limit": "256 megabytes",
  "statement": "Mashmokh's boss, Bimokh, didn't like Mashmokh. So he fired him. Mashmokh decided to go to university and participate in ACM instead of finding a new job. He wants to become a member of Bamokh's team. In order to join he was given some programming tasks and one week to solve them. Mashmokh is not a very experienced programmer. Actually he is not a programmer at all. So he wasn't able to solve them. That's why he asked you to help him with these tasks. One of these tasks is the following.\nA sequence of l integers b1, b2, ..., bl (1 ≤ b1 ≤ b2 ≤ ... ≤ bl ≤ n) is called good if each number divides (without a remainder) by the next number in the sequence. More formally  for all i (1 ≤ i ≤ l - 1).\nGiven n and k find the number of good sequences of length k. As the answer can be rather large print it modulo 1000000007 (109 + 7).",
  "input": "Input",
  "output": "",
  "samples": [],
  "note": "",
  "hints": [],
  "tutorial": ""
}