{
  "id": "463E",
  "contest_id": 463,
  "index": "E",
  "name": "Caisa and Tree",
  "difficulty": 2100,
  "tags": [
    "brute force",
    "dfs and similar",
    "math",
    "number theory",
    "trees"
  ],
  "url": "https://codeforces.com/problemset/problem/463/E",
  "time_limit": "10 seconds",
  "memory_limit": "256 megabytes",
  "statement": "Caisa is now at home and his son has a simple task for him.\nGiven a rooted tree with n vertices, numbered from 1 to n (vertex 1 is the root). Each vertex of the tree has a value. You should answer q queries. Each query is one of the following:\n•  Format of the query is \"1 v\". Let's write out the sequence of vertices along the path from the root to vertex v: u1, u2, ..., uk (u1 = 1; uk = v). You need to output such a vertex ui that gcd(value of ui, value of v) \u003e 1 and i \u003c k. If there are several possible vertices ui pick the one with maximum value of i. If there is no such vertex output -1.\n•  Format of the query is \"2 v w\". You must change the value of vertex v to w.\nYou are given all the queries, help Caisa to solve the problem.",
  "input": "Input",
  "output": "",
  "samples": [],
  "note": "",
  "hints": [],
  "tutorial": ""
}