{
  "id": "478C",
  "contest_id": 478,
  "index": "C",
  "name": "Table Decorations",
  "difficulty": 1800,
  "tags": [
    "greedy"
  ],
  "url": "https://codeforces.com/problemset/problem/478/C",
  "time_limit": "1 second",
  "memory_limit": "256 megabytes",
  "statement": "You have r red, g green and b blue balloons. To decorate a single table for the banquet you need exactly three balloons. Three balloons attached to some table shouldn't have the same color. What maximum number t of tables can be decorated if we know number of balloons of each color?\nYour task is to write a program that for given values r, g and b will find the maximum number t of tables, that can be decorated in the required manner.",
  "input": "Input",
  "output": "",
  "samples": [],
  "note": "",
  "hints": [],
  "tutorial": ""
}