{
  "id": "558D",
  "contest_id": 558,
  "index": "D",
  "name": "Guess Your Way Out! II",
  "difficulty": 2300,
  "tags": [
    "data structures",
    "implementation",
    "sortings"
  ],
  "url": "https://codeforces.com/problemset/problem/558/D",
  "time_limit": "2 seconds",
  "memory_limit": "256 megabytes",
  "statement": "Amr bought a new video game \"Guess Your Way Out! II\". The goal of the game is to find an exit from the maze that looks like a perfect binary tree of height h. The player is initially standing at the root of the tree and the exit from the tree is located at some leaf node.\nLet's index all the nodes of the tree such that\n•  The root is number 1\n•  Each internal node i (i ≤ 2h - 1 - 1) will have a left child with index = 2i and a right child with index = 2i + 1\nThe level of a node is defined as 1 for a root, or 1 + level of parent of the node otherwise. The vertices of the level h are called leaves. The exit to the maze is located at some leaf node n, the player doesn't know where the exit is so he has to guess his way out!\nIn the new version of the game the player is allowed to ask questions on the format \"Does the ancestor(exit, i) node number belong to the range [L, R]?\". Here ancestor(v, i) is the ancestor of a node v that located in the level i. The game will answer with \"Yes\" or \"No\" only. The game is designed such that it doesn't always answer correctly, and sometimes it cheats to confuse the player!.\nAmr asked a lot of questions and got confused by all these answers, so he asked you to help him. Given the questions and its answers, can you identify whether the game is telling contradictory information or not? If the information is not contradictory and the exit node can be determined uniquely, output its number. If the information is not contradictory, but the exit node isn't defined uniquely, output that the number of questions is not sufficient. Otherwise output that the information is contradictory.",
  "input": "Input",
  "output": "",
  "samples": [],
  "note": "",
  "hints": [],
  "tutorial": ""
}