{
  "id": "587E",
  "contest_id": 587,
  "index": "E",
  "name": "Duff as a Queen",
  "difficulty": 2900,
  "tags": [
    "data structures"
  ],
  "url": "https://codeforces.com/problemset/problem/587/E",
  "time_limit": "7 seconds",
  "memory_limit": "256 megabytes",
  "statement": "Duff is the queen of her country, Andarz Gu. She's a competitive programming fan. That's why, when he saw her minister, Malek, free, she gave her a sequence consisting of n non-negative integers, a1, a2, ..., an and asked him to perform q queries for her on this sequence.\nThere are two types of queries:\n•  given numbers l, r and k, Malek should perform  for each l ≤ i ≤ r (, bitwise exclusive OR of numbers a and b).\n•  given numbers l and r Malek should tell her the score of sequence al, al + 1, ... , ar.\nScore of a sequence b1, ..., bk is the number of its different Kheshtaks. A non-negative integer w is a Kheshtak of this sequence if and only if there exists a subsequence of b, let's denote it as bi1, bi2, ... , bix (possibly empty) such that  (1 ≤ i1 \u003c i2 \u003c ... \u003c ix ≤ k). If this subsequence is empty, then w = 0.\nUnlike Duff, Malek is not a programmer. That's why he asked for your help. Please help him perform these queries.",
  "input": "Input",
  "output": "",
  "samples": [],
  "note": "",
  "hints": [],
  "tutorial": ""
}