{
  "id": "605C",
  "contest_id": 605,
  "index": "C",
  "name": "Freelancer's Dreams",
  "difficulty": 2400,
  "tags": [
    "geometry"
  ],
  "url": "https://codeforces.com/problemset/problem/605/C",
  "time_limit": "2 seconds",
  "memory_limit": "256 megabytes",
  "statement": "Mikhail the Freelancer dreams of two things: to become a cool programmer and to buy a flat in Moscow. To become a cool programmer, he needs at least p experience points, and a desired flat in Moscow costs q dollars. Mikhail is determined to follow his dreams and registered at a freelance site.\nHe has suggestions to work on n distinct projects. Mikhail has already evaluated that the participation in the i-th project will increase his experience by ai per day and bring bi dollars per day. As freelance work implies flexible working hours, Mikhail is free to stop working on one project at any time and start working on another project. Doing so, he receives the respective share of experience and money. Mikhail is only trying to become a cool programmer, so he is able to work only on one project at any moment of time.\nFind the real value, equal to the minimum number of days Mikhail needs to make his dream come true.\nFor example, suppose Mikhail is suggested to work on three projects and a1 = 6, b1 = 2, a2 = 1, b2 = 3, a3 = 2, b3 = 6. Also, p = 20 and q = 20. In order to achieve his aims Mikhail has to work for 2.5 days on both first and third projects. Indeed, a1·2.5 + a2·0 + a3·2.5 = 6·2.5 + 1·0 + 2·2.5 = 20 and b1·2.5 + b2·0 + b3·2.5 = 2·2.5 + 3·0 + 6·2.5 = 20.",
  "input": "Input",
  "output": "",
  "samples": [],
  "note": "",
  "hints": [],
  "tutorial": ""
}