{
  "id": "702E",
  "contest_id": 702,
  "index": "E",
  "name": "Analysis of Pathes in Functional Graph",
  "difficulty": 2100,
  "tags": [
    "data structures",
    "graphs"
  ],
  "url": "https://codeforces.com/problemset/problem/702/E",
  "time_limit": "2 seconds",
  "memory_limit": "512 megabytes",
  "statement": "You are given a functional graph. It is a directed graph, in which from each vertex goes exactly one arc. The vertices are numerated from 0 to n - 1.\nGraph is given as the array f0, f1, ..., fn - 1, where fi — the number of vertex to which goes the only arc from the vertex i. Besides you are given array with weights of the arcs w0, w1, ..., wn - 1, where wi — the arc weight from i to fi.\nThe graph from the first sample test.\nAlso you are given the integer k (the length of the path) and you need to find for each vertex two numbers si and mi, where:\n•  si — the sum of the weights of all arcs of the path with length equals to k which starts from the vertex i;\n•  mi — the minimal weight from all arcs on the path with length k which starts from the vertex i.\nThe length of the path is the number of arcs on this path.",
  "input": "Input",
  "output": "",
  "samples": [],
  "note": "",
  "hints": [],
  "tutorial": ""
}