{
  "id": "797F",
  "contest_id": 797,
  "index": "F",
  "name": "Mice and Holes",
  "difficulty": 2600,
  "tags": [
    "data structures",
    "dp",
    "greedy",
    "sortings"
  ],
  "url": "https://codeforces.com/problemset/problem/797/F",
  "time_limit": "1.5 seconds",
  "memory_limit": "256 megabytes",
  "statement": "One day Masha came home and noticed n mice in the corridor of her flat. Of course, she shouted loudly, so scared mice started to run to the holes in the corridor.\nThe corridor can be represeted as a numeric axis with n mice and m holes on it. ith mouse is at the coordinate xi, and jth hole — at coordinate pj. jth hole has enough room for cj mice, so not more than cj mice can enter this hole.\nWhat is the minimum sum of distances that mice have to go through so that they all can hide in the holes? If ith mouse goes to the hole j, then its distance is |xi - pj|.\nPrint the minimum sum of distances.",
  "input": "The first line contains two integer numbers n, m (1 ≤ n, m ≤ 5000) — the number of mice and the number of holes, respectively.\nThe second line contains n integers x1, x2, ..., xn ( - 109 ≤ xi ≤ 109), where xi is the coordinate of ith mouse.\nNext m lines contain pairs of integer numbers pj, cj ( - 109 ≤ pj ≤ 109, 1 ≤ cj ≤ 5000), where pj is the coordinate of jth hole, and cj is the maximum number of mice that can hide in the hole j.",
  "output": "Print one integer number — the minimum sum of distances. If there is no solution, print -1 instead.",
  "samples": [
    {
      "input": "4 5\n6 2 8 9\n3 6\n2 1\n3 6\n4 7\n4 7",
      "output": "11"
    },
    {
      "input": "7 2\n10 20 30 40 50 45 35\n-1000000000 10\n1000000000 1",
      "output": "7000000130"
    }
  ],
  "note": "",
  "hints": [],
  "tutorial": ""
}