{
  "id": "97A",
  "contest_id": 97,
  "index": "A",
  "name": "Domino",
  "difficulty": 2400,
  "tags": [
    "brute force",
    "implementation"
  ],
  "url": "https://codeforces.com/problemset/problem/97/A",
  "time_limit": "0.5 second",
  "memory_limit": "256 megabytes",
  "statement": "Little Gennady was presented with a set of domino for his birthday. The set consists of 28 different dominoes of size 2 × 1. Both halves of each domino contain one digit from 0 to 6.\n0-0 0-1 0-2 0-3 0-4 0-5 0-6\n1-1 1-2 1-3 1-4 1-5 1-6\n2-2 2-3 2-4 2-5 2-6\n3-3 3-4 3-5 3-6\n4-4 4-5 4-6\n5-5 5-6\n6-6\nThe figure that consists of 28 dominoes is called magic, if it can be fully covered with 14 non-intersecting squares of size 2 × 2 so that each square contained four equal numbers. Every time Gennady assembles a magic figure, some magic properties of the set appear — he wins the next contest. Gennady noticed that he can't assemble a figure that has already been assembled, otherwise someone else wins the contest.\nGennady chose a checked field of size n × m and put there rectangular chips of sizes 1 × 2 and 2 × 1. Each chip fully occupies exactly two neighboring squares of the field. Those chips do not overlap but they can touch each other. Overall the field has exactly 28 chips, equal to the number of dominoes in the set. Now Gennady wants to replace each chip with a domino so that a magic figure appeared as a result. Different chips should be replaced by different dominoes. Determine in what number of contests Gennady can win over at the given position of the chips. You are also required to find one of the possible ways of replacing chips with dominoes to win the next Codeforces round.",
  "input": "Input",
  "output": "",
  "samples": [],
  "note": "",
  "hints": [],
  "tutorial": ""
}